columnarframe/__init__.py
columnarframe/column.py
columnarframe/concat.py
columnarframe/frame.py
columnarframe/read_csv.py
columnarframe/read_excel.py
columnarframe/utils.py
columnarframe-0.7.0.dist-info/METADATA
columnarframe-0.7.0.dist-info/WHEEL
columnarframe-0.7.0.dist-info/LICENSE
columnarframe-0.7.0.dist-info/RECORD
